[{"column_count":3,"row_count":3,"cell_data":["ＣＵＴ","Ａ■Ｐ","ＴＷＯ"],"hints":{"h":[[1,"ＣＵＴ","【動】切る【名】切れ目"],[2,"ＴＷＯ","【名】二"]],"v":[[2,"ＣＡＴ","【名】ネコ"],[3,"ＴＰＯ","【略語】時・場所・場合に応じるという考え方"]]},"id":"1uEnojQkD5l8yS8WUGK1"},{"column_count":3,"row_count":3,"cell_data":["ＧＥＴ","Ｏ■Ａ","ＤＯＧ"],"hints":{"h":[[1,"ＧＥＴ","【動】取得する，受け取る"],[2,"ＤＯＧ","【名】犬"]],"v":[[2,"ＧＯＤ","【名】神"],[3,"ＴＡＧ","【名】タグ，荷札，鬼ごっこ"]]},"id":"56RydUYFgRaw2rsCM5Zu"},{"column_count":3,"row_count":3,"cell_data":["ＡＬＬ","Ｔ■Ｏ","■ＧＷ"],"hints":{"h":[[1,"ＡＬＬ","【形】すべて"],[4,"ＧＷ","【略語】ゴールデンウィーク"]],"v":[[2,"ＡＴ","【略語】自動変速機"],[3,"ＬＯＷ","【形】低い"]]},"id":"5hRy28NufUilGybCdeiA"},{"column_count":3,"row_count":3,"cell_data":["ＡＮＤ","Ｔ■Ａ","■ＤＭ"],"hints":{"h":[[1,"ＡＮＤ","【接】…と～，…そして～"],[4,"ＤＭ","【略語】ダイレクトメール"]],"v":[[2,"ＡＴ","【略語】自動変速機"],[3,"ＤＡＭ","【名】ダム，堰"]]},"id":"EleCIyg6f7oQQvr1GjRK"},{"column_count":3,"row_count":3,"cell_data":["ＢＡＧ","Ａ■Ｅ","ＲＡＴ"],"hints":{"h":[[1,"ＢＡＧ","【名】袋"],[2,"ＲＡＴ","【名】ねずみ"]],"v":[[1,"ＢＡＲ","【名】棒，横木"],[3,"ＧＥＴ","【動】取得する，受け取る"]]},"id":"GTptGVLhJmJVfcKhw0Oz"},{"column_count":3,"row_count":3,"cell_data":["ＥＮＤ","Ａ■Ａ","ＲＥＤ"],"hints":{"h":[[1,"ＥＮＤ","【名】終了【動】おわる，止める"],[3,"ＲＥＤ","【形】赤い【名】赤"]],"v":[[2,"ＥＡＲ","【名】耳"],[4,"ＤＡＤ","【名】パパ"]]},"id":"I7QLnUq5x9N7nAoB4EIf"},{"column_count":3,"row_count":3,"cell_data":["ＢＡＤ","Ａ■Ａ","ＴＯＹ"],"hints":{"h":[[1,"ＢＡＤ","【形】悪い"],[2,"ＴＯＹ","【名】おもちゃ"]],"v":[[1,"ＢＡＴ","【名】コウモリ，（野球の）バット"],[3,"ＤＡＹ","【名】日"]]},"id":"MTkwYC1XS5Dl8mLqsbVj"},{"column_count":3,"row_count":3,"cell_data":["ＤＡＹ","Ｏ■Ｅ","ＴＥＮ"],"hints":{"h":[[1,"ＤＡＹ","【名】日"],[2,"ＴＥＮ","10"]],"v":[[2,"ＤＯＴ","【名】点"],[3,"ＹＥＮ","【名】円（えん）"]]},"id":"W43ShYkcLu59ErBrpKFx"},{"column_count":3,"row_count":3,"cell_data":["ＡＲＴ","Ｔ■Ａ","■ＧＢ"],"hints":{"h":[[1,"ＡＲＴ","【名】芸術"],[4,"ＧＢ","【略語】ギガバイト"]],"v":[[2,"ＡＴ","【略語】自動変速機"],[3,"ＴＡＢ","【名】タブ，つまみ"]]},"id":"bPpOEOMDXNjAjIZjCipJ"},{"column_count":3,"row_count":3,"cell_data":["ＢＩＧ","Ｉ■Ｍ","ＴＶ■"],"hints":{"h":[[1,"ＢＩＧ","【名】大きい"],[2,"ＴＶ","【名】テレビ"]],"v":[[1,"ＢＩＴ","【名】小片，少し"],[3,"ＧＭ","【略語】ゼネラルマネージャー"]]},"id":"zvdqvLN17NREKPuiuE8s"}]